django_react_views/__init__.py
django_react_views/apps.py
django_react_views/tests.py
django_react_views/views.py
django_react_views/templates/react/react_full.html
django_react_views/templates/react/react_root.html
django_react_views/templates/react/react_scripts.html
django_react_views/templatetags/__init__.py
django_react_views/templatetags/react.py
django_react_views-1.1.dist-info/METADATA
django_react_views-1.1.dist-info/RECORD
django_react_views-1.1.dist-info/WHEEL
django_react_views-1.1.dist-info/top_level.txt
